megaconvert/__init__.py
megaconvert/api.py
megaconvert/cli.py
megaconvert/core.py
megaconvert/errors.py
megaconvert/registry.py
megaconvert/types.py
megaconvert/plugins/__init__.py
megaconvert/plugins/archives.py
megaconvert/plugins/base.py
megaconvert/plugins/calibre.py
megaconvert/plugins/comics.py
megaconvert/plugins/djvu.py
megaconvert/plugins/ffmpeg.py
megaconvert/plugins/ghostscript.py
megaconvert/plugins/imagemagick.py
megaconvert/plugins/inkscape.py
megaconvert/plugins/libreoffice.py
megaconvert/plugins/pandoc.py
megaconvert/plugins/pdf_basic.py
megaconvert/plugins/text_structured.py
megaconvert/utils/__init__.py
megaconvert/utils/files.py
megaconvert/utils/sh.py
megaconvert/utils/which.py
megaconvert-0.2.1.dist-info/licenses/LICENSE
megaconvert-0.2.1.dist-info/METADATA
megaconvert-0.2.1.dist-info/WHEEL
megaconvert-0.2.1.dist-info/entry_points.txt
megaconvert-0.2.1.dist-info/top_level.txt
megaconvert-0.2.1.dist-info/RECORD
