Metadata-Version: 2.4
Name: megaconvert
Version: 0.2.1
Summary: Advanced plugin-based file conversion toolkit (CLI + Python API).
Requires-Python: >=3.10
License-File: LICENSE
Requires-Dist: pillow>=10.0.0
Requires-Dist: pypdf>=4.0.0
Provides-Extra: ocr
Requires-Dist: pytesseract>=0.3.10; extra == "ocr"
Provides-Extra: yaml
Requires-Dist: PyYAML>=6.0.1; extra == "yaml"
Provides-Extra: toml
Requires-Dist: tomli>=2.0.1; python_version < "3.11" and extra == "toml"
Provides-Extra: xml
Requires-Dist: lxml>=5.2.0; extra == "xml"
Provides-Extra: json
Provides-Extra: dev
Requires-Dist: pytest>=8.0.0; extra == "dev"
Requires-Dist: ruff>=0.5.0; extra == "dev"
Dynamic: license-file
